nsj_sql_utils_lib/__init__.py
nsj_sql_utils_lib/dao_util.py
nsj_sql_utils_lib/dbadapter3.py
nsj_sql_utils_lib/dbconnection.py
nsj_sql_utils_lib/dbconnection_mysql_connector.py
nsj_sql_utils_lib/dbconnection_psycopg2.py
nsj_sql_utils_lib/updater/__init__.py
nsj_sql_utils_lib/updater/create_script.py
nsj_sql_utils_lib/updater/db_updater.py
nsj_sql_utils_lib/updater/erp_database_updater.py
nsj_sql_utils_lib/updater/vars.py
nsj_sql_utils_lib-2.1.3.dist-info/METADATA
nsj_sql_utils_lib-2.1.3.dist-info/WHEEL
nsj_sql_utils_lib-2.1.3.dist-info/top_level.txt
nsj_sql_utils_lib-2.1.3.dist-info/RECORD
