Metadata-Version: 2.4
Name: nsj_sql_utils_lib
Version: 2.1.3
Summary: Biblioteca de utilitários Python para facilitar a implementação de sistemas com acesso a banco de dados.
Home-page: https://github.com/Nasajon/nsj-sql-utils-lib
Author: Nasajon Sistemas
Author-email: contact.dev@nasajon.com.br
Project-URL: Source, https://github.com/Nasajon/nsj-sql-utils-lib
Classifier: Development Status :: 3 - Alpha
Classifier: Intended Audience :: Developers
Classifier: Topic :: Software Development :: Libraries
Classifier: Programming Language :: Python :: 3
Requires-Python: >=3.4
Requires-Dist: psycopg2_binary>=2.9.6
Requires-Dist: SQLAlchemy>=1.4.32
Requires-Dist: sqlparams>=3.0.0
Requires-Dist: mysql-connector-python>=8.4.0
Requires-Dist: python-logging-loki>=0.3.1
